setup.py
appViews/__init__.py
appViews/main/L_main.py
appViews/main/Ui_main.py
appViews/main/__init__.py
pyuts/__docker__.py
pyuts/__init__.py
pyuts/__main__.py
pyuts/__setup__.py
pyuts/py_api_b.py
pyuts.egg-info/PKG-INFO
pyuts.egg-info/SOURCES.txt
pyuts.egg-info/dependency_links.txt
pyuts.egg-info/requires.txt
pyuts.egg-info/top_level.txt
pyuts/py_app/__init__.py
pyuts/py_app/appU.py
pyuts/py_app/ui2pyU.py
pyuts/py_app/windowU.py
pyuts/py_crawl/__init__.py
pyuts/py_crawl/__main__.py
pyuts/py_crawl/chromeU.py
pyuts/py_crawl/httpU.py
pyuts/py_crawl/recordU.py
pyuts/py_crawl/scrapyCommandDemo.py
pyuts/py_crawl/scrapyCommandU.py
pyuts/py_crawl/scrapyCrawlDemo.py
pyuts/py_crawl/scrapyItemU.py
pyuts/py_crawl/scrapyMiddleware.py
pyuts/py_crawl/scrapyPipline.py
pyuts/py_crawl/scrapyRunU.py
pyuts/py_crawl/scrapySaveItem.py
pyuts/py_crawl/scrapySettings.py
pyuts/py_crawl/scrapySpiderDemo.py
pyuts/py_crawl/scrapySpiderU.py
pyuts/py_crawl/scrapyU.py
pyuts/py_crawl/webU.py
pyuts/py_db/__init__.py
pyuts/py_db/mongoDBU.py
pyuts/py_db/mysqlDBU.py
pyuts/py_db/mysqlU.py
pyuts/py_db/redisDBU.py
pyuts/py_file/__init__.py
pyuts/py_file/fileU.py
pyuts/py_file/videoU.py
pyuts/py_mix/__init__.py
pyuts/py_mix/algorithmU.py
pyuts/py_mix/asyncU.py
pyuts/py_mix/cmdU.py
pyuts/py_mix/ctrlCU.py
pyuts/py_mix/datetimeU.py
pyuts/py_mix/envU.py
pyuts/py_mix/jsU.py
pyuts/py_mix/jsonU.py
pyuts/py_mix/mathU.py
pyuts/py_mix/moduleU.py
pyuts/py_mix/objU.py
pyuts/py_mix/sortU.py
pyuts/py_mix/speechBaiduU.py
pyuts/py_mix/speechU.py
pyuts/py_mix/threadU.py
pyuts/py_mix/xmlU.py
pyuts/py_pfm/__init__.py
pyuts/py_pfm/modelU.py
pyuts/py_pfm/pfmU.py
pyuts/py_phone/__init__.py
pyuts/py_phone/__main__.py
pyuts/py_phone/adbU.py
pyuts/py_phone/phoneAutoU.py
pyuts/py_proxy/__init__.py
pyuts/py_proxy/proxyCrawlerU.py
pyuts/py_proxy/proxyInfoU.py
pyuts/py_proxy/proxyU.py
pyuts/py_recg/__init__.py
pyuts/py_recg/imgU.py
pyuts/py_recg/ocr/__init__.py
pyuts/py_recg/speech/__init__.py
pyuts/py_recg/speech/aliyun.py
pyuts/py_recg/speech/baidu.py
pyuts/py_server/__init__.py
pyuts/py_server/httpHandlerU.py
pyuts/py_server/httpServerU.py
pyuts/py_server/serverU.py