Metadata-Version: 1.0
Name: pyuts
Version: 0.0.32
Summary: dbtool,timetool,filetool,phonetool,servertool
Home-page: UNKNOWN
Author: Jack
Author-email: m846999958@gmail.com
License: MIT Licence
Keywords: pip,pathtool,timetool,phonetool,pyuts,pyuts
Platform: any
